{"id": "20260701-093645", "start": 1782873405.7957103, "end": 1782873426.2777324, "duration_s": 20.5, "frames": [{"rear": 0, "auto": 0, "dnL": 4, "dnR": 0, "ang": 102, "gz": 0, "dist": 33.8, "ast": 0, "spd": 200, "ticks": 4, "dL": 2, "mv": 0, "safe": 1, "_t": 136}, {"rear": 0, "auto": 0, "dnL": 0, "dnR": 0, "ang": 120, "gz": 0, "dist": 33.8, "ast": 0, "spd": 200, "ticks": 4, "dL": 0, "mv": 0, "safe": 1, "_t": 338}, {"rear": 0, "auto": 0, "dnL": 0, "dnR": 0, "ang": 138, "gz": 0, "dist": 33.8, "ast": 0, "spd": 200, "ticks": 4, "dL": 0, "mv": 0, "safe": 1, "_t": 519}, {"rear": 0, "auto": 0, "dnL": 0, "dnR": 0, "ang": 150, "gz": 0, "dist": 33.8, "ast": 0, "spd": 200, "ticks": 4, "dL": 0, "mv": 0, "safe": 1, "_t": 599}, {"rear": 0, "auto": 0, "dnL": 0, "dnR": 0, "ang": 138, "gz": 0, "dist": 34.6, "ast": 0, "spd": 200, "ticks": 4, "dL": 0, "mv": 0, "safe": 1, "_t": 1626}, {"rear": 0, "auto": 0, "dnL": 0, "dnR": 0, "ang": 120, "gz": 0, "dist": 33.8, "ast": 0, "spd": 200, "ticks": 4, "dL": 0, "mv": 0, "safe": 1, "_t": 1626}, {"rear": 0, "auto": 0, "dnL": 0, "dnR": 0, "ang": 102, "gz": 0, "dist": 33.3, "ast": 0, "spd": 200, "ticks": 4, "dL": 0, "mv": 0, "safe": 1, "_t": 1626}, {"rear": 0, "auto": 0, "dnL": 0, "dnR": 0, "ang": 90, "gz": 0, "dist": 32.8, "ast": 0, "spd": 200, "ticks": 4, "dL": 0, "mv": 0, "safe": 1, "_t": 1626}, {"rear": 0, "auto": 0, "dnL": 0, "dnR": 0, "ang": 72, "gz": 0, "dist": 32.8, "ast": 0, "spd": 200, "ticks": 4, "dL": 0, "mv": 0, "safe": 1, "_t": 1626}, {"rear": 0, "auto": 0, "dnL": 0, "dnR": 0, "ang": 60, "gz": 0, "dist": 33.3, "ast": 0, "spd": 200, "ticks": 4, "dL": 0, "mv": 0, "safe": 1, "_t": 1626}, {"rear": 0, "auto": 0, "dnL": 0, "dnR": 0, "ang": 42, "gz": 0, "dist": 33.3, "ast": 0, "spd": 200, "ticks": 4, "dL": 0, "mv": 0, "safe": 1, "_t": 1955}, {"rear": 0, "auto": 0, "dnL": 0, "dnR": 0, "ang": 30, "gz": 0, "dist": 33.8, "ast": 0, "spd": 200, "ticks": 4, "dL": 0, "mv": 0, "safe": 1, "_t": 1955}, {"rear": 0, "auto": 0, "dnL": 0, "dnR": 0, "ang": 48, "gz": 0, "dist": 53.0, "ast": 0, "spd": 200, "ticks": 4, "dL": 0, "mv": 0, "safe": 1, "_t": 2251}, {"rear": 0, "auto": 0, "dnL": 0, "dnR": 0, "ang": 60, "gz": 0, "dist": 42.9, "ast": 0, "spd": 200, "ticks": 4, "dL": 0, "mv": 0, "safe": 1, "_t": 2251}, {"rear": 0, "auto": 0, "dnL": 0, "dnR": 0, "ang": 78, "gz": 0, "dist": 42.3, "ast": 0, "spd": 200, "ticks": 4, "dL": 0, "mv": 0, "safe": 1, "_t": 2562}, {"rear": 0, "auto": 0, "dnL": 0, "dnR": 0, "ang": 90, "gz": 0, "dist": 42.3, "ast": 0, "spd": 200, "ticks": 4, "dL": 0, "mv": 0, "safe": 1, "_t": 2562}, {"rear": 0, "auto": 0, "dnL": 0, "dnR": 0, "ang": 108, "gz": 0, "dist": 34.4, "ast": 0, "spd": 200, "ticks": 4, "dL": 0, "mv": 0, "safe": 1, "_t": 2865}, {"rear": 0, "auto": 0, "dnL": 0, "dnR": 0, "ang": 120, "gz": 0, "dist": 32.3, "ast": 0, "spd": 200, "ticks": 4, "dL": 0, "mv": 0, "safe": 1, "_t": 2865}, {"rear": 0, "auto": 0, "dnL": 0, "dnR": 0, "ang": 138, "gz": 0, "dist": 32.3, "ast": 0, "spd": 200, "ticks": 4, "dL": 0, "mv": 0, "safe": 1, "_t": 3176}, {"rear": 0, "auto": 0, "dnL": 0, "dnR": 0, "ang": 150, "gz": 0, "dist": 32.3, "ast": 0, "spd": 200, "ticks": 4, "dL": 0, "mv": 0, "safe": 1, "_t": 3176}, {"rear": 0, "auto": 0, "dnL": 0, "dnR": 0, "ang": 138, "gz": 0, "dist": 32.3, "ast": 0, "spd": 200, "ticks": 4, "dL": 0, "mv": 0, "safe": 1, "_t": 3176}, {"rear": 0, "auto": 0, "dnL": 0, "dnR": 0, "ang": 120, "gz": 0, "dist": 32.3, "ast": 0, "spd": 200, "ticks": 4, "dL": 0, "mv": 0, "safe": 1, "_t": 3482}, {"rear": 0, "auto": 0, "dnL": 0, "dnR": 0, "ang": 108, "gz": 0, "dist": 32.3, "ast": 0, "spd": 200, "ticks": 4, "dL": 0, "mv": 0, "safe": 1, "_t": 3874}, {"rear": 0, "auto": 0, "dnL": 0, "dnR": 0, "ang": 102, "gz": 0, "dist": 32.3, "ast": 0, "spd": 200, "ticks": 4, "dL": 0, "mv": 0, "safe": 1, "_t": 4096}, {"rear": 0, "auto": 0, "dnL": 0, "dnR": 0, "ang": 90, "gz": 0, "dist": 32.2, "ast": 0, "spd": 200, "ticks": 4, "dL": 0, "mv": 0, "safe": 1, "_t": 4096}, {"rear": 1, "auto": 0, "dnL": 0, "dnR": 0, "ang": 72, "gz": 0, "dist": 32.2, "ast": 0, "spd": 200, "ticks": 4, "dL": 0, "mv": 0, "safe": 1, "_t": 4486}, {"rear": 1, "auto": 0, "dnL": 0, "dnR": 0, "ang": 60, "gz": 0, "dist": 32.3, "ast": 0, "spd": 200, "ticks": 4, "dL": 0, "mv": 0, "safe": 1, "_t": 4486}, {"rear": 1, "auto": 0, "dnL": 0, "dnR": 0, "ang": 42, "gz": 0, "dist": 42.2, "ast": 0, "spd": 200, "ticks": 4, "dL": 0, "mv": 0, "safe": 1, "_t": 4535}, {"rear": 1, "auto": 0, "dnL": 0, "dnR": 0, "ang": 30, "gz": 0, "dist": 42.7, "ast": 0, "spd": 200, "ticks": 4, "dL": 0, "mv": 0, "safe": 1, "_t": 4633}, {"rear": 1, "auto": 0, "dnL": 0, "dnR": 0, "ang": 48, "gz": 0, "dist": 42.7, "ast": 0, "spd": 200, "ticks": 4, "dL": 0, "mv": 0, "safe": 1, "_t": 4796}, {"rear": 1, "auto": 0, "dnL": 0, "dnR": 0, "ang": 60, "gz": 0, "dist": 42.7, "ast": 0, "spd": 200, "ticks": 4, "dL": 0, "mv": 0, "safe": 1, "_t": 4935}, {"rear": 1, "auto": 0, "dnL": 0, "dnR": 0, "ang": 78, "gz": 0, "dist": 42.7, "ast": 0, "spd": 200, "ticks": 4, "dL": 0, "mv": 0, "safe": 1, "_t": 5101}, {"rear": 0, "auto": 0, "dnL": 0, "dnR": 0, "ang": 90, "gz": 0, "dist": 42.7, "ast": 0, "spd": 200, "ticks": 4, "dL": 0, "mv": 0, "safe": 1, "_t": 5229}, {"rear": 0, "auto": 0, "dnL": 0, "dnR": 0, "ang": 108, "gz": 0, "dist": 42.7, "ast": 0, "spd": 200, "ticks": 4, "dL": 0, "mv": 0, "safe": 1, "_t": 5408}, {"rear": 0, "auto": 0, "dnL": 0, "dnR": 0, "ang": 126, "gz": 0, "dist": 32.3, "ast": 0, "spd": 200, "ticks": 4, "dL": 0, "mv": 0, "safe": 1, "_t": 5541}, {"rear": 0, "auto": 0, "dnL": 0, "dnR": 0, "ang": 138, "gz": 0, "dist": 32.3, "ast": 0, "spd": 200, "ticks": 4, "dL": 0, "mv": 0, "safe": 1, "_t": 5715}, {"rear": 0, "auto": 0, "dnL": 0, "dnR": 0, "ang": 144, "gz": 0, "dist": 32.3, "ast": 0, "spd": 200, "ticks": 4, "dL": 0, "mv": 0, "safe": 1, "_t": 5857}, {"rear": 0, "auto": 0, "dnL": 0, "dnR": 0, "ang": 132, "gz": 0, "dist": 32.3, "ast": 0, "spd": 200, "ticks": 4, "dL": 0, "mv": 0, "safe": 1, "_t": 6136}, {"rear": 0, "auto": 0, "dnL": 0, "dnR": 0, "ang": 120, "gz": 0, "dist": 32.3, "ast": 0, "spd": 200, "ticks": 4, "dL": 0, "mv": 0, "safe": 1, "_t": 6245}, {"rear": 0, "auto": 0, "dnL": 0, "dnR": 0, "ang": 108, "gz": 0, "dist": 32.3, "ast": 0, "spd": 200, "ticks": 4, "dL": 0, "mv": 0, "safe": 1, "_t": 6333}, {"rear": 0, "auto": 0, "dnL": 0, "dnR": 0, "ang": 90, "gz": 0, "dist": 32.3, "ast": 0, "spd": 200, "ticks": 4, "dL": 0, "mv": 0, "safe": 1, "_t": 6554}, {"rear": 0, "auto": 0, "dnL": 0, "dnR": 0, "ang": 78, "gz": 0, "dist": 32.3, "ast": 0, "spd": 200, "ticks": 4, "dL": 0, "mv": 0, "safe": 1, "_t": 6640}, {"rear": 0, "auto": 0, "dnL": 0, "dnR": 0, "ang": 66, "gz": 0, "dist": 32.2, "ast": 0, "spd": 200, "ticks": 4, "dL": 0, "mv": 0, "safe": 1, "_t": 6761}, {"rear": 0, "auto": 0, "dnL": 0, "dnR": 0, "ang": 48, "gz": 0, "dist": 42.2, "ast": 0, "spd": 200, "ticks": 4, "dL": 0, "mv": 0, "safe": 1, "_t": 6882}, {"rear": 0, "auto": 0, "dnL": 0, "dnR": 0, "ang": 36, "gz": 0, "dist": 42.3, "ast": 0, "spd": 200, "ticks": 4, "dL": 0, "mv": 0, "safe": 1, "_t": 7483}, {"rear": 0, "auto": 0, "dnL": 0, "dnR": 0, "ang": 30, "gz": 0, "dist": 42.3, "ast": 0, "spd": 200, "ticks": 4, "dL": 0, "mv": 0, "safe": 1, "_t": 7562}, {"rear": 0, "auto": 0, "dnL": 0, "dnR": 0, "ang": 42, "gz": 0, "dist": 44.8, "ast": 0, "spd": 200, "ticks": 4, "dL": 0, "mv": 0, "safe": 1, "_t": 7782}, {"rear": 0, "auto": 0, "dnL": 0, "dnR": 0, "ang": 60, "gz": 0, "dist": 44.8, "ast": 0, "spd": 200, "ticks": 4, "dL": 0, "mv": 0, "safe": 1, "_t": 7782}, {"rear": 0, "auto": 0, "dnL": 0, "dnR": 0, "ang": 72, "gz": 0, "dist": 41.8, "ast": 0, "spd": 200, "ticks": 4, "dL": 0, "mv": 0, "safe": 1, "_t": 8120}, {"rear": 0, "auto": 0, "dnL": 0, "dnR": 0, "ang": 90, "gz": 0, "dist": 41.8, "ast": 0, "spd": 200, "ticks": 4, "dL": 0, "mv": 0, "safe": 1, "_t": 8120}, {"rear": 0, "auto": 0, "dnL": 0, "dnR": 0, "ang": 102, "gz": 0, "dist": 32.8, "ast": 0, "spd": 200, "ticks": 4, "dL": 0, "mv": 0, "safe": 1, "_t": 8218}, {"rear": 0, "auto": 0, "dnL": 0, "dnR": 0, "ang": 120, "gz": 0, "dist": 32.3, "ast": 0, "spd": 200, "ticks": 4, "dL": 0, "mv": 0, "safe": 1, "_t": 8380}, {"rear": 0, "auto": 0, "dnL": 0, "dnR": 0, "ang": 132, "gz": 0, "dist": 32.3, "ast": 0, "spd": 200, "ticks": 4, "dL": 0, "mv": 0, "safe": 1, "_t": 8711}, {"rear": 0, "auto": 0, "dnL": 0, "dnR": 0, "ang": 150, "gz": 0, "dist": 32.8, "ast": 0, "spd": 200, "ticks": 4, "dL": 0, "mv": 0, "safe": 1, "_t": 8790}, {"rear": 0, "auto": 0, "dnL": 0, "dnR": 0, "ang": 138, "gz": 0, "dist": 32.8, "ast": 0, "spd": 200, "ticks": 4, "dL": 0, "mv": 0, "safe": 1, "_t": 8836}, {"rear": 0, "auto": 0, "dnL": 0, "dnR": 0, "ang": 126, "gz": 0, "dist": 36.2, "ast": 0, "spd": 200, "ticks": 4, "dL": 0, "mv": 0, "safe": 1, "_t": 9011}, {"rear": 0, "auto": 0, "dnL": 0, "dnR": 0, "ang": 108, "gz": 0, "dist": 33.8, "ast": 0, "spd": 200, "ticks": 4, "dL": 0, "mv": 0, "safe": 1, "_t": 9115}, {"rear": 0, "auto": 0, "dnL": 0, "dnR": 0, "ang": 90, "gz": 0, "dist": 33.3, "ast": 0, "spd": 200, "ticks": 4, "dL": 0, "mv": 0, "safe": 1, "_t": 9424}, {"rear": 0, "auto": 0, "dnL": 0, "dnR": 0, "ang": 78, "gz": 0, "dist": 32.8, "ast": 0, "spd": 200, "ticks": 4, "dL": 0, "mv": 0, "safe": 1, "_t": 9814}, {"rear": 0, "auto": 0, "dnL": 0, "dnR": 0, "ang": 72, "gz": 0, "dist": 33.3, "ast": 0, "spd": 200, "ticks": 4, "dL": 0, "mv": 0, "safe": 1, "_t": 9861}, {"rear": 0, "auto": 0, "dnL": 0, "dnR": 0, "ang": 60, "gz": 0, "dist": 33.8, "ast": 0, "spd": 200, "ticks": 4, "dL": 0, "mv": 0, "safe": 1, "_t": 10125}, {"rear": 0, "auto": 0, "dnL": 0, "dnR": 0, "ang": 42, "gz": 0, "dist": 33.8, "ast": 0, "spd": 200, "ticks": 4, "dL": 0, "mv": 0, "safe": 1, "_t": 10222}, {"rear": 0, "auto": 0, "dnL": 0, "dnR": 0, "ang": 36, "gz": 0, "dist": 36.2, "ast": 0, "spd": 200, "ticks": 4, "dL": 0, "mv": 0, "safe": 1, "_t": 10547}, {"rear": 0, "auto": 0, "dnL": 0, "dnR": 0, "ang": 48, "gz": 0, "dist": 44.8, "ast": 0, "spd": 200, "ticks": 4, "dL": 0, "mv": 0, "safe": 1, "_t": 10547}, {"rear": 0, "auto": 0, "dnL": 0, "dnR": 0, "ang": 66, "gz": 0, "dist": 42.7, "ast": 0, "spd": 200, "ticks": 4, "dL": 0, "mv": 0, "safe": 1, "_t": 10857}, {"rear": 0, "auto": 0, "dnL": 0, "dnR": 0, "ang": 78, "gz": 0, "dist": 42.3, "ast": 0, "spd": 200, "ticks": 4, "dL": 0, "mv": 0, "safe": 1, "_t": 10857}, {"rear": 0, "auto": 0, "dnL": 0, "dnR": 0, "ang": 96, "gz": 0, "dist": 42.3, "ast": 0, "spd": 200, "ticks": 4, "dL": 0, "mv": 0, "safe": 1, "_t": 11283}, {"rear": 0, "auto": 0, "dnL": 0, "dnR": 0, "ang": 102, "gz": 0, "dist": 42.3, "ast": 0, "spd": 200, "ticks": 4, "dL": 0, "mv": 0, "safe": 1, "_t": 11469}, {"rear": 0, "auto": 0, "dnL": 0, "dnR": 0, "ang": 114, "gz": 0, "dist": 32.3, "ast": 0, "spd": 200, "ticks": 4, "dL": 0, "mv": 0, "safe": 1, "_t": 11469}, {"rear": 0, "auto": 0, "dnL": 0, "dnR": 0, "ang": 132, "gz": 0, "dist": 32.3, "ast": 0, "spd": 200, "ticks": 4, "dL": 0, "mv": 0, "safe": 1, "_t": 11775}, {"rear": 0, "auto": 0, "dnL": 0, "dnR": 0, "ang": 144, "gz": 0, "dist": 32.8, "ast": 0, "spd": 200, "ticks": 4, "dL": 0, "mv": 0, "safe": 1, "_t": 11775}, {"rear": 0, "auto": 0, "dnL": 0, "dnR": 0, "ang": 138, "gz": 0, "dist": 36.2, "ast": 0, "spd": 200, "ticks": 4, "dL": 0, "mv": 0, "safe": 1, "_t": 12084}, {"rear": 0, "auto": 0, "dnL": 0, "dnR": 0, "ang": 126, "gz": 0, "dist": 37.8, "ast": 0, "spd": 200, "ticks": 4, "dL": 0, "mv": 0, "safe": 1, "_t": 12084}, {"rear": 0, "auto": 0, "dnL": 0, "dnR": 0, "ang": 108, "gz": 0, "dist": 35.1, "ast": 0, "spd": 200, "ticks": 4, "dL": 0, "mv": 0, "safe": 1, "_t": 12390}, {"rear": 0, "auto": 0, "dnL": 0, "dnR": 0, "ang": 90, "gz": 0, "dist": 33.8, "ast": 0, "spd": 200, "ticks": 4, "dL": 0, "mv": 0, "safe": 1, "_t": 12390}, {"rear": 0, "auto": 0, "dnL": 0, "dnR": 0, "ang": 78, "gz": 0, "dist": 32.8, "ast": 0, "spd": 200, "ticks": 4, "dL": 0, "mv": 0, "safe": 1, "_t": 12699}, {"rear": 0, "auto": 0, "dnL": 0, "dnR": 0, "ang": 60, "gz": 0, "dist": 33.3, "ast": 0, "spd": 200, "ticks": 4, "dL": 0, "mv": 0, "safe": 1, "_t": 12783}, {"rear": 0, "auto": 0, "dnL": 0, "dnR": 0, "ang": 48, "gz": 0, "dist": 33.0, "ast": 0, "spd": 200, "ticks": 4, "dL": 0, "mv": 0, "safe": 1, "_t": 12831}, {"rear": 0, "auto": 0, "dnL": 0, "dnR": 0, "ang": 36, "gz": 0, "dist": 34.3, "ast": 0, "spd": 200, "ticks": 4, "dL": 0, "mv": 0, "safe": 1, "_t": 12988}, {"rear": 0, "auto": 0, "dnL": 0, "dnR": 0, "ang": 42, "gz": 0, "dist": 43.6, "ast": 0, "spd": 200, "ticks": 4, "dL": 0, "mv": 0, "safe": 1, "_t": 13527}, {"rear": 0, "auto": 0, "dnL": 0, "dnR": 0, "ang": 48, "gz": 0, "dist": 43.6, "ast": 0, "spd": 200, "ticks": 4, "dL": 0, "mv": 0, "safe": 1, "_t": 13628}, {"rear": 0, "auto": 0, "dnL": 0, "dnR": 0, "ang": 60, "gz": 0, "dist": 42.5, "ast": 0, "spd": 200, "ticks": 4, "dL": 0, "mv": 0, "safe": 1, "_t": 13731}, {"rear": 0, "auto": 0, "dnL": 0, "dnR": 0, "ang": 78, "gz": 0, "dist": 42.7, "ast": 0, "spd": 200, "ticks": 4, "dL": 0, "mv": 0, "safe": 1, "_t": 13834}, {"rear": 0, "auto": 0, "dnL": 0, "dnR": 0, "ang": 96, "gz": 0, "dist": 36.2, "ast": 0, "spd": 200, "ticks": 4, "dL": 0, "mv": 0, "safe": 1, "_t": 14420}, {"rear": 0, "auto": 0, "dnL": 0, "dnR": 0, "ang": 102, "gz": 0, "dist": 36.2, "ast": 0, "spd": 200, "ticks": 4, "dL": 0, "mv": 0, "safe": 1, "_t": 14471}, {"rear": 0, "auto": 0, "dnL": 0, "dnR": 0, "ang": 114, "gz": 0, "dist": 32.8, "ast": 0, "spd": 200, "ticks": 4, "dL": 0, "mv": 0, "safe": 1, "_t": 14544}, {"rear": 0, "auto": 0, "dnL": 0, "dnR": 0, "ang": 132, "gz": 0, "dist": 32.8, "ast": 0, "spd": 200, "ticks": 4, "dL": 0, "mv": 0, "safe": 1, "_t": 14727}, {"rear": 0, "auto": 0, "dnL": 0, "dnR": 0, "ang": 144, "gz": 0, "dist": 32.8, "ast": 0, "spd": 200, "ticks": 4, "dL": 0, "mv": 0, "safe": 1, "_t": 14850}, {"rear": 0, "auto": 0, "dnL": 0, "dnR": 0, "ang": 138, "gz": 0, "dist": 33.3, "ast": 0, "spd": 200, "ticks": 4, "dL": 0, "mv": 0, "safe": 1, "_t": 15154}, {"rear": 0, "auto": 0, "dnL": 0, "dnR": 0, "ang": 120, "gz": 0, "dist": 36.7, "ast": 0, "spd": 200, "ticks": 4, "dL": 0, "mv": 0, "safe": 1, "_t": 15154}, {"rear": 0, "auto": 0, "dnL": 0, "dnR": 0, "ang": 108, "gz": 0, "dist": 32.8, "ast": 0, "spd": 200, "ticks": 4, "dL": 0, "mv": 0, "safe": 1, "_t": 15463}, {"rear": 0, "auto": 0, "dnL": 0, "dnR": 0, "ang": 90, "gz": 0, "dist": 32.3, "ast": 0, "spd": 200, "ticks": 4, "dL": 0, "mv": 0, "safe": 1, "_t": 15463}, {"rear": 0, "auto": 0, "dnL": 0, "dnR": 0, "ang": 72, "gz": 0, "dist": 32.8, "ast": 0, "spd": 200, "ticks": 4, "dL": 0, "mv": 0, "safe": 1, "_t": 15790}, {"rear": 0, "auto": 0, "dnL": 0, "dnR": 0, "ang": 60, "gz": 0, "dist": 32.8, "ast": 0, "spd": 200, "ticks": 4, "dL": 0, "mv": 0, "safe": 1, "_t": 15790}, {"rear": 0, "auto": 0, "dnL": 0, "dnR": 0, "ang": 42, "gz": 0, "dist": 42.0, "ast": 0, "spd": 200, "ticks": 4, "dL": 0, "mv": 0, "safe": 1, "_t": 16277}, {"rear": 0, "auto": 0, "dnL": 0, "dnR": 0, "ang": 36, "gz": 0, "dist": 42.5, "ast": 0, "spd": 200, "ticks": 4, "dL": 0, "mv": 0, "safe": 1, "_t": 16389}, {"rear": 0, "auto": 0, "dnL": 0, "dnR": 0, "ang": 36, "gz": 0, "dist": 44.8, "ast": 0, "spd": 200, "ticks": 4, "dL": 0, "mv": 0, "safe": 1, "_t": 16497}, {"rear": 0, "auto": 0, "dnL": 0, "dnR": 0, "ang": 54, "gz": 0, "dist": 44.8, "ast": 0, "spd": 200, "ticks": 4, "dL": 0, "mv": 0, "safe": 1, "_t": 16693}, {"rear": 0, "auto": 0, "dnL": 0, "dnR": 0, "ang": 72, "gz": 0, "dist": 42.0, "ast": 0, "spd": 200, "ticks": 4, "dL": 0, "mv": 0, "safe": 1, "_t": 16785}, {"rear": 0, "auto": 0, "dnL": 0, "dnR": 0, "ang": 84, "gz": 0, "dist": 34.9, "ast": 0, "spd": 200, "ticks": 4, "dL": 0, "mv": 0, "safe": 1, "_t": 16895}, {"rear": 0, "auto": 0, "dnL": 0, "dnR": 0, "ang": 102, "gz": 0, "dist": 34.4, "ast": 0, "spd": 200, "ticks": 4, "dL": 0, "mv": 0, "safe": 1, "_t": 17083}, {"rear": 0, "auto": 0, "dnL": 0, "dnR": 0, "ang": 114, "gz": 0, "dist": 32.3, "ast": 0, "spd": 200, "ticks": 4, "dL": 0, "mv": 0, "safe": 1, "_t": 17198}, {"rear": 0, "auto": 0, "dnL": 0, "dnR": 0, "ang": 132, "gz": 0, "dist": 32.2, "ast": 0, "spd": 200, "ticks": 4, "dL": 0, "mv": 0, "safe": 1, "_t": 17502}, {"rear": 0, "auto": 0, "dnL": 0, "dnR": 0, "ang": 150, "gz": 0, "dist": 32.3, "ast": 0, "spd": 200, "ticks": 4, "dL": 0, "mv": 0, "safe": 1, "_t": 17594}, {"rear": 0, "auto": 0, "dnL": 0, "dnR": 0, "ang": 138, "gz": 0, "dist": 33.8, "ast": 0, "spd": 200, "ticks": 4, "dL": 0, "mv": 0, "safe": 1, "_t": 17699}, {"rear": 0, "auto": 0, "dnL": 0, "dnR": 0, "ang": 120, "gz": 0, "dist": 36.2, "ast": 0, "spd": 200, "ticks": 4, "dL": 0, "mv": 0, "safe": 1, "_t": 17812}, {"rear": 0, "auto": 0, "dnL": 0, "dnR": 0, "ang": 108, "gz": 0, "dist": 33.3, "ast": 0, "spd": 200, "ticks": 4, "dL": 0, "mv": 0, "safe": 1, "_t": 18004}, {"rear": 0, "auto": 0, "dnL": 0, "dnR": 0, "ang": 90, "gz": 0, "dist": 32.3, "ast": 0, "spd": 200, "ticks": 4, "dL": 0, "mv": 0, "safe": 1, "_t": 18233}, {"rear": 0, "auto": 0, "dnL": 0, "dnR": 0, "ang": 78, "gz": 0, "dist": 32.8, "ast": 0, "spd": 200, "ticks": 4, "dL": 0, "mv": 0, "safe": 1, "_t": 18334}, {"rear": 0, "auto": 0, "dnL": 0, "dnR": 0, "ang": 66, "gz": 0, "dist": 32.8, "ast": 0, "spd": 200, "ticks": 4, "dL": 0, "mv": 0, "safe": 1, "_t": 18534}, {"rear": 0, "auto": 0, "dnL": 0, "dnR": 0, "ang": 54, "gz": 0, "dist": 32.8, "ast": 0, "spd": 200, "ticks": 4, "dL": 0, "mv": 0, "safe": 1, "_t": 18620}, {"rear": 0, "auto": 0, "dnL": 0, "dnR": 0, "ang": 36, "gz": 0, "dist": 42.0, "ast": 0, "spd": 200, "ticks": 4, "dL": 0, "mv": 0, "safe": 1, "_t": 19129}, {"rear": 0, "auto": 0, "dnL": 0, "dnR": 0, "ang": 30, "gz": 0, "dist": 42.7, "ast": 0, "spd": 200, "ticks": 4, "dL": 0, "mv": 0, "safe": 1, "_t": 19481}, {"rear": 0, "auto": 0, "dnL": 0, "dnR": 0, "ang": 42, "gz": 0, "dist": 44.4, "ast": 0, "spd": 200, "ticks": 4, "dL": 0, "mv": 0, "safe": 1, "_t": 19481}, {"rear": 0, "auto": 0, "dnL": 0, "dnR": 0, "ang": 60, "gz": 0, "dist": 42.9, "ast": 0, "spd": 200, "ticks": 4, "dL": 0, "mv": 0, "safe": 1, "_t": 19481}, {"rear": 0, "auto": 0, "dnL": 0, "dnR": 0, "ang": 78, "gz": 0, "dist": 42.3, "ast": 0, "spd": 200, "ticks": 4, "dL": 0, "mv": 0, "safe": 1, "_t": 19762}, {"rear": 0, "auto": 0, "dnL": 0, "dnR": 0, "ang": 90, "gz": 0, "dist": 42.3, "ast": 0, "spd": 200, "ticks": 4, "dL": 0, "mv": 0, "safe": 1, "_t": 19762}, {"rear": 0, "auto": 0, "dnL": 0, "dnR": 0, "ang": 102, "gz": 0, "dist": 32.8, "ast": 0, "spd": 200, "ticks": 4, "dL": 0, "mv": 0, "safe": 1, "_t": 20070}, {"rear": 0, "auto": 0, "dnL": 0, "dnR": 0, "ang": 108, "gz": 0, "dist": 32.8, "ast": 0, "spd": 200, "ticks": 4, "dL": 0, "mv": 0, "safe": 1, "_t": 20070}]}